I2C_Autotest/__init__.py
I2C_Autotest/analytics_core.py
I2C_Autotest-1.0.2.dist-info/LICENSE
I2C_Autotest-1.0.2.dist-info/METADATA
I2C_Autotest-1.0.2.dist-info/WHEEL
I2C_Autotest-1.0.2.dist-info/top_level.txt
I2C_Autotest-1.0.2.dist-info/RECORD
